setup.py
BinomialandGaussian/Binomialdistribution.py
BinomialandGaussian/Gaussiandistribution.py
BinomialandGaussian/GeneralDistribution.py
BinomialandGaussian/__init__.py
BinomialandGaussian.egg-info/PKG-INFO
BinomialandGaussian.egg-info/SOURCES.txt
BinomialandGaussian.egg-info/dependency_links.txt
BinomialandGaussian.egg-info/not-zip-safe
BinomialandGaussian.egg-info/top_level.txt