Metadata-Version: 1.0
Name: BinomialandGaussian
Version: 1.3
Summary: Gaussian and Binomial distributions
Home-page: UNKNOWN
Author: Mosin Mahajan
Author-email: mosinmahajan@gmail.com
License: UNKNOWN
Platform: UNKNOWN
